{"cameraMode":{"drawMode":0,"name":"Shaded","section":"Shading Mode"},"sceneLighting":true,"audioPlay":false,"sceneViewState":{"showFog":true,"showMaterialUpdate":false,"showSkybox":true,"showFlares":true,"showImageEffects":true,"showParticleSystems":true},"in2DMode":false,"pivot":{"x":2.2403125762939455,"y":1.4740564823150635,"z":4.604410171508789},"rotation":{"x":-0.2786320447921753,"y":0.12117649614810944,"z":-0.03546326979994774,"w":-0.9520658850669861},"size":11.700672149658204,"orthographic":false}